cheeky_platform_shared/__init__.py
cheeky_platform_shared/llm.py
cheeky_platform_shared/prompts.py
cheeky_platform_shared-0.1.1.dist-info/METADATA
cheeky_platform_shared-0.1.1.dist-info/WHEEL
cheeky_platform_shared-0.1.1.dist-info/top_level.txt
cheeky_platform_shared-0.1.1.dist-info/RECORD
