Metadata-Version: 2.4
Name: cheeky-platform-shared
Version: 0.1.1
Summary: Shared utilities for Cheeky Platform - AI-powered Shopify analytics
Author-email: Cheeky Platform Team <team@cheeky.com>
License: MIT
Project-URL: Homepage, https://github.com/cheeky-platform/cheeky-platform
Project-URL: Bug Reports, https://github.com/cheeky-platform/cheeky-platform/issues
Project-URL: Source, https://github.com/cheeky-platform/cheeky-platform
Keywords: cheeky,shopify,analytics,ai
Classifier: Development Status :: 3 - Alpha
Classifier: Intended Audience :: Developers
Classifier: License :: OSI Approved :: MIT License
Classifier: Programming Language :: Python :: 3
Classifier: Programming Language :: Python :: 3.10
Classifier: Programming Language :: Python :: 3.11
Classifier: Programming Language :: Python :: 3.12
Requires-Python: >=3.10
Requires-Dist: httpx>=0.25.0
